infomaniak_ai/__about__.py
infomaniak_ai/__init__.py
infomaniak_ai/session.py
infomaniak_ai/openai/__init__.py
infomaniak_ai/openai/audio/__init__.py
infomaniak_ai/openai/audio/transcriptions.py
infomaniak_ai/openai/chat/__init__.py
infomaniak_ai/openai/chat/completions.py
infomaniak_ai-0.0.1.dist-info/METADATA
infomaniak_ai-0.0.1.dist-info/WHEEL
infomaniak_ai-0.0.1.dist-info/licenses/LICENSE
infomaniak_ai-0.0.1.dist-info/RECORD
